{
  "collectionName": "components_order_addresses",
  "info": {
    "name": "address",
    "icon": "map-pin"
  },
  "options": {},
  "attributes": {
    "district": {
      "type": "string",
      "required": true,
      "maxLength": 64
    },
    "division": {
      "type": "string",
      "maxLength": 64,
      "required": true
    },
    "subdistrict": {
      "type": "string",
      "maxLength": 64,
      "required": true
    },
    "streetAddress": {
      "type": "text"
    },
    "charge": {
      "type": "decimal",
      "max": 999,
      "min": 0
    }
  }
}
